uplite/__init__.py
uplite/datalang.py
uplite/flow.py
uplite/lake.py
uplite/py.typed
uplite-1.0.1.dist-info/WHEEL
uplite-1.0.1.dist-info/METADATA
uplite-1.0.1.dist-info/RECORD
