Metadata-Version: 2.3
Name: uplite
Version: 1.0.1
Summary: Typed data workflows on Spark and Delta Lake
Author: Krzysztof Sadowski
Author-email: Krzysztof Sadowski <krzysztof@sadowski.tech>
License: Proprietary License. See https://www.uplite.tech/license
Requires-Dist: boto3>=1.42.0
Requires-Dist: delta-spark>=3.3.0
Requires-Dist: pyspark>=3.5.0,<=3.5.5
Requires-Dist: typing-extensions>=4.15.0
Requires-Python: >=3.12
